titanfit/__init__.py
titanfit/titanfit.py
titanfit-0.0.3.dist-info/LICENSE.txt
titanfit-0.0.3.dist-info/METADATA
titanfit-0.0.3.dist-info/WHEEL
titanfit-0.0.3.dist-info/top_level.txt
titanfit-0.0.3.dist-info/RECORD
