Metadata-Version: 2.1
Name: titanfit
Version: 0.0.3
Summary: Titan spectra fitter
Home-page: UNKNOWN
Author: Charlie Blue Arm
Author-email: cbluearm22@amherst.edu
License: UNKNOWN
Platform: UNKNOWN
Classifier: Programming Language :: Python :: 3
Classifier: License :: OSI Approved :: MIT License
Classifier: Operating System :: OS Independent
Requires-Python: >=3.6
